pcss_qapi/__init__.py
pcss_qapi/auth/__init__.py
pcss_qapi/auth/auth_service.py
pcss_qapi/auth/connections.py
pcss_qapi/auth/oauth_flow.py
pcss_qapi/base/__init__.py
pcss_qapi/base/connection_base.py
pcss_qapi/base/job_base.py
pcss_qapi/base/provider_base.py
pcss_qapi/orca/__init__.py
pcss_qapi/orca/backend.py
pcss_qapi/orca/orca_task.py
pcss_qapi/orca/provider.py
pcss_qapi/orca/ptseries_integration/__init__.py
pcss_qapi/orca/ptseries_integration/pt_adapter.py
pcss_qapi/utils/__init__.py
pcss_qapi/utils/exceptions.py
pcss_qapi/utils/fs_manager.py
pcss_qapi/utils/requests.py
pcss_qapi-0.1.3.dist-info/METADATA
pcss_qapi-0.1.3.dist-info/WHEEL
pcss_qapi-0.1.3.dist-info/top_level.txt
pcss_qapi-0.1.3.dist-info/RECORD
