Metadata-Version: 2.4
Name: pcss_qapi
Version: 0.1.3
Summary: Python client for pcss quantum api
Requires-Python: >=3.11
Requires-Dist: numpy==1.26.4
Requires-Dist: pyjwt>=2.10.1
Requires-Dist: requests>=2.32.3
Provides-Extra: orca
Requires-Dist: torch>=2.7.0; extra == "orca"
Requires-Dist: torchaudio>=2.7.0; extra == "orca"
Requires-Dist: torchvision>=0.22.0; extra == "orca"
